helpers/excel.py
helpers/netbox.py
netbox_loadtest.py
netbox_loadtest-2.0.1.dist-info/entry_points.txt
netbox_loadtest-2.0.1.dist-info/LICENSE
netbox_loadtest-2.0.1.dist-info/WHEEL
netbox_loadtest-2.0.1.dist-info/METADATA
netbox_loadtest-2.0.1.dist-info/RECORD
