Metadata-Version: 2.1
Name: netbox-loadtest
Version: 2.0.1
Summary: A load test script for the netbox IPAM solution.
Home-page: https://github.com/jjmanzer/netbox-loadtest/
License: MIT
Author: Jarrod J Manzer
Author-email: jjmanzer@godaddy.com
Requires-Python: >=3.6.1,<4.0.0
Classifier: Development Status :: 3 - Alpha
Classifier: Environment :: Web Environment
Classifier: Intended Audience :: Developers
Classifier: License :: OSI Approved :: MIT License
Classifier: Natural Language :: English
Classifier: Operating System :: OS Independent
Classifier: Programming Language :: Python
Classifier: Programming Language :: Python :: 3
Classifier: Programming Language :: Python :: 3.6
Classifier: Programming Language :: Python :: 3.7
Classifier: Programming Language :: Python :: 3.8
Requires-Dist: openpyxl (>=3.0.3,<4.0.0)
Requires-Dist: requests (>=2.23.0,<3.0.0)
Project-URL: Repository, https://github.com/jjmanzer/netbox-loadtest/
